remin/__init__.py
remin/callbacks.py
remin/domain.py
remin/func.py
remin/residual.py
remin/solver/__init__.py
remin/solver/residual_loss.py
remin/solver/solver.py
remin/solver/trainer.py
remin/utils/__init__.py
remin/utils/mesh.py
remin-0.2.7.dist-info/LICENSE
remin-0.2.7.dist-info/METADATA
remin-0.2.7.dist-info/WHEEL
remin-0.2.7.dist-info/entry_points.txt
remin-0.2.7.dist-info/top_level.txt
remin-0.2.7.dist-info/RECORD
