Metadata-Version: 2.1
Name: remin
Version: 0.2.7
Summary: PINN solver implemented in Pytorch
Author-email: Salih Taşdelen <salih.tasdelen@hotmail.com>
Project-URL: Homepage, https://github.com/SalihTasdelen/remin
Project-URL: Bug Tracker, https://github.com/SalihTasdelen/remin/issues
Classifier: Programming Language :: Python :: 3
Classifier: License :: OSI Approved :: MIT License
Classifier: Operating System :: OS Independent
Requires-Python: >=3.7
License-File: LICENSE
Requires-Dist: torch >=2.0.0
Requires-Dist: pyDOE >=0.3.8
Requires-Dist: pyevtk >=1.6.0
Requires-Dist: numpy
Provides-Extra: dev
Requires-Dist: pylint ~=2.14.0 ; extra == 'dev'
Requires-Dist: toml ~=0.10.2 ; extra == 'dev'
Requires-Dist: yapf ~=0.32.0 ; extra == 'dev'
